envdiff.py
envset.py
envdiff_tool-0.1.2.dist-info/licenses/LICENSE
envdiff_tool-0.1.2.dist-info/METADATA
envdiff_tool-0.1.2.dist-info/WHEEL
envdiff_tool-0.1.2.dist-info/entry_points.txt
envdiff_tool-0.1.2.dist-info/top_level.txt
envdiff_tool-0.1.2.dist-info/RECORD
