Metadata-Version: 2.4
Name: envdiff-tool
Version: 0.1.2
Summary: Diff & patch environment configs across local/remote (.env, YAML, config.py) plus single-key editor.
Author-email: Talaat Magdy <talaatmagdy75@gmail.com>
License: MIT
Project-URL: Homepage, https://github.com/talaatmagdyx/envdiff_fresh
Project-URL: Repository, https://github.com/talaatmagdyx/envdiff_fresh
Keywords: environment,config,diff,yaml,dotenv,ssh,remote,cli,configuration-management,env-files
Classifier: Development Status :: 4 - Beta
Classifier: Intended Audience :: Developers
Classifier: Intended Audience :: System Administrators
Classifier: License :: OSI Approved :: MIT License
Classifier: Operating System :: OS Independent
Classifier: Programming Language :: Python :: 3
Classifier: Programming Language :: Python :: 3.8
Classifier: Programming Language :: Python :: 3.9
Classifier: Programming Language :: Python :: 3.10
Classifier: Programming Language :: Python :: 3.11
Classifier: Programming Language :: Python :: 3.12
Classifier: Topic :: Software Development :: Libraries :: Python Modules
Classifier: Topic :: System :: Systems Administration
Classifier: Topic :: Utilities
Requires-Python: >=3.8
License-File: LICENSE
Requires-Dist: PyYAML>=6.0
Provides-Extra: dev
Requires-Dist: pytest>=7.4; extra == "dev"
Requires-Dist: pytest-cov>=4.1; extra == "dev"
Requires-Dist: ruff>=0.6.0; extra == "dev"
Dynamic: license-file
